{
  "country": "Panama",
  "last_updated": "2026-04-04T00:01:05.433559+00:00",
  "story_count": 6,
  "stories": [
    {
      "title": "US lifts sanctions on Venezuelan interim leader Delcy Rodríguez",
      "source": "BBC News",
      "url": "https://www.bbc.com/news/articles/cje4l9de0d1o?at_medium=RSS&at_campaign=rss",
      "published_date": "2026-04-02T11:55:37+00:00",
      "category": "Diplomacy"
    },
    {
      "title": "At least 16 killed, thousands displaced by gang attack in rural Haiti",
      "source": "BBC News",
      "url": "https://www.bbc.com/news/articles/cql76l4221qo?at_medium=RSS&at_campaign=rss",
      "published_date": "2026-03-31T12:02:46+00:00",
      "category": "Military"
    },
    {
      "title": "Cuba begins releasing more than 2,000 prisoners as US pressure mounts",
      "source": "BBC News",
      "url": "https://www.bbc.com/news/articles/cwy3r3w4zl8o?at_medium=RSS&at_campaign=rss",
      "published_date": "2026-04-03T20:59:48+00:00",
      "category": "Energy"
    },
    {
      "title": "Russian oil tanker docks in Cuba ending near-total blockade",
      "source": "BBC News",
      "url": "https://www.bbc.com/news/articles/clyx1lrv0w5o?at_medium=RSS&at_campaign=rss",
      "published_date": "2026-03-31T12:51:51+00:00",
      "category": "Energy"
    },
    {
      "title": "Russian oil tanker reaches Cuba after Trump appears to loosen blockade",
      "source": "BBC News",
      "url": "https://www.bbc.com/news/articles/czrevyx28z2o?at_medium=RSS&at_campaign=rss",
      "published_date": "2026-03-30T14:46:15+00:00",
      "category": "Energy"
    },
    {
      "title": "'The gravest crime against humanity': What does the UN vote on slavery mean?",
      "source": "BBC News",
      "url": "https://www.bbc.com/news/articles/c0rxqng5pyno?at_medium=RSS&at_campaign=rss",
      "published_date": "2026-03-28T01:06:54+00:00",
      "category": "Local Events"
    }
  ]
}